hydxlib/__init__.py
hydxlib/exporter.py
hydxlib/hydx.py
hydxlib/importer.py
hydxlib/scripts.py
hydxlib/threedi.py
hydxlib/tests/__init__.py
hydxlib/tests/conftest.py
hydxlib/tests/test_exporter.py
hydxlib/tests/test_hydx.py
hydxlib/tests/test_importer.py
hydxlib/tests/test_scripts.py
hydxlib/tests/test_threedi.py
hydxlib-1.7.4.dist-info/licenses/LICENSE
hydxlib-1.7.4.dist-info/METADATA
hydxlib-1.7.4.dist-info/WHEEL
hydxlib-1.7.4.dist-info/entry_points.txt
hydxlib-1.7.4.dist-info/top_level.txt
hydxlib-1.7.4.dist-info/RECORD
