Metadata-Version: 2.4
Name: hydxlib
Version: 1.7.4
Summary: Importer and Exporter for GWSW
Home-page: https://github.com/nens/hydxlib
Author: Nelen & Schuurmans
Author-email: info@nelen-schuurmans.nl
License: MIT
Classifier: Programming Language :: Python
Requires-Python: >=3.9
License-File: LICENSE
Requires-Dist: sqlalchemy
Requires-Dist: threedi-schema==0.300.*,>=0.300.18
Requires-Dist: pyproj>=3
Requires-Dist: geoalchemy2[shapely]
Provides-Extra: test
Requires-Dist: pytest; extra == "test"
Requires-Dist: pytest-cov; extra == "test"
Dynamic: author
Dynamic: author-email
Dynamic: classifier
Dynamic: description
Dynamic: home-page
Dynamic: license
Dynamic: license-file
Dynamic: provides-extra
Dynamic: requires-dist
Dynamic: requires-python
Dynamic: summary
